ChangeLog.md
LICENSE
MANIFEST.in
README.md
SECURITY.md
requirements.txt
setup.py
tox.ini
examples/Get-GPPPassword.py
examples/GetADUsers.py
examples/GetNPUsers.py
examples/GetUserSPNs.py
examples/PoC.py
examples/PoC2.py
examples/addcomputer.py
examples/atexec.py
examples/dcomexec.py
examples/dpapi.py
examples/esentutl.py
examples/exchanger.py
examples/findDelegation.py
examples/getArch.py
examples/getPac.py
examples/getST.py
examples/getTGT.py
examples/goldenPac.py
examples/karmaSMB.py
examples/keylistattack2.py
examples/kintercept.py
examples/lookupsid.py
examples/mimikatz.py
examples/mqtt_check.py
examples/mssqlclient.py
examples/mssqlinstance.py
examples/netview.py
examples/nmapAnswerMachine.py
examples/ntfs-read.py
examples/ntlmrelayx.py
examples/ping.py
examples/ping6.py
examples/psexec.py
examples/raiseChild.py
examples/rbcd.py
examples/rdp_check.py
examples/reg.py
examples/registry-read.py
examples/rpcdump.py
examples/rpcmap.py
examples/sambaPipe.py
examples/samrdump.py
examples/secretsdump.py
examples/services.py
examples/smbclient.py
examples/smbexec.py
examples/smbpasswd.py
examples/smbrelayx.py
examples/smbserver.py
examples/sniff.py
examples/sniffer.py
examples/split.py
examples/testTGT.py
examples/testTGT2.py
examples/ticketConverter.py
examples/ticketer.py
examples/wmiexec.py
examples/wmipersist.py
examples/wmiquery.py
impacket/Dot11Crypto.py
impacket/Dot11KeyManager.py
impacket/ICMP6.py
impacket/IP6.py
impacket/IP6_Address.py
impacket/IP6_Extension_Headers.py
impacket/ImpactDecoder.py
impacket/ImpactPacket.py
impacket/NDP.py
impacket/__init__.py
impacket/cdp.py
impacket/crypto.py
impacket/dhcp.py
impacket/dns.py
impacket/dot11.py
impacket/dpapi.py
impacket/eap.py
impacket/ese.py
impacket/helper.py
impacket/hresult_errors.py
impacket/http.py
impacket/mapi_constants.py
impacket/mqtt.py
impacket/nmb.py
impacket/nt_errors.py
impacket/ntlm.py
impacket/pcap_linktypes.py
impacket/pcapfile.py
impacket/smb.py
impacket/smb3.py
impacket/smb3structs.py
impacket.egg-info/PKG-INFO
impacket.egg-info/SOURCES.txt
impacket.egg-info/dependency_links.txt
impacket.egg-info/requires.txt
impacket.egg-info/top_level.txt
