Metadata-Version: 2.1
Name: impacket
Version: 0.9.24
Summary: Network protocols Constructors and Dissectors
Home-page: https://www.secureauth.com/labs/open-source-tools/impacket
Author: SecureAuth Corporation
Author-email: oss@secureauth.com
Maintainer: SecureAuth's Innovation Labs 
Maintainer-email: oss@secureauth.com
License: Apache modified
Platform: Unix
Platform: Windows
Classifier: Programming Language :: Python :: 3.9
Classifier: Programming Language :: Python :: 3.8
Classifier: Programming Language :: Python :: 3.7
Classifier: Programming Language :: Python :: 3.6
Classifier: Programming Language :: Python :: 2.7
Provides-Extra: pyreadline
